methodaws/__init__.py
methodaws/core/__init__.py
methodaws/core/datetime_utils.py
methodaws/core/enum.py
methodaws/core/pydantic_utilities.py
methodaws/core/serialization.py
methodaws/py.typed
methodaws/resources/__init__.py
methodaws/resources/apigateway/__init__.py
methodaws/resources/apigateway/resources/__init__.py
methodaws/resources/apigateway/resources/enumerate/__init__.py
methodaws/resources/apigateway/resources/enumerate/access_log_settings.py
methodaws/resources/apigateway/resources/enumerate/api_gateway_configuration_info.py
methodaws/resources/apigateway/resources/enumerate/api_gateway_enumerate_config.py
methodaws/resources/apigateway/resources/enumerate/api_gateway_enumerate_report.py
methodaws/resources/apigateway/resources/enumerate/api_gateway_enumerate_result.py
methodaws/resources/apigateway/resources/enumerate/api_gateway_identification_info.py
methodaws/resources/apigateway/resources/enumerate/api_gateway_instance.py
methodaws/resources/apigateway/resources/enumerate/api_gateway_resource_info.py
methodaws/resources/apigateway/resources/enumerate/api_gateway_security.py
methodaws/resources/apigateway/resources/enumerate/api_gateway_version.py
methodaws/resources/apigateway/resources/enumerate/authorization_type.py
methodaws/resources/apigateway/resources/enumerate/authorizer.py
methodaws/resources/apigateway/resources/enumerate/aws_integration.py
methodaws/resources/apigateway/resources/enumerate/aws_proxy_integration.py
methodaws/resources/apigateway/resources/enumerate/aws_service_backend.py
methodaws/resources/apigateway/resources/enumerate/certificate.py
methodaws/resources/apigateway/resources/enumerate/cors_configuration.py
methodaws/resources/apigateway/resources/enumerate/endpoint_type.py
methodaws/resources/apigateway/resources/enumerate/http_backend.py
methodaws/resources/apigateway/resources/enumerate/http_integration.py
methodaws/resources/apigateway/resources/enumerate/http_proxy_integration.py
methodaws-0.0.67.dist-info/METADATA
methodaws-0.0.67.dist-info/WHEEL
methodaws-0.0.67.dist-info/RECORD
